dora_kit_car/__init__.py
dora_kit_car/dora_kit_car.pyd
dora_kit_car-0.4.1.dist-info/METADATA
dora_kit_car-0.4.1.dist-info/WHEEL
dora_kit_car-0.4.1.dist-info/entry_points.txt
dora_kit_car-0.4.1.dist-info/RECORD
