Metadata-Version: 2.4
Name: dora-kit-car
Version: 0.4.1
Summary: Dora Node for dora kit car
Author-email: Leon <echo_ai@foxmail.com>
License: MIT
Requires-Python: >=3.8
